dopplrSDKtest/__init__.py
dopplrSDKtest/pyarmor_runtime_000000/__init__.py
dopplrSDKtest/pyarmor_runtime_000000/pyarmor_runtime.pyd
dopplrSDKtest-1.11.dist-info/LICENSE.txt
dopplrSDKtest-1.11.dist-info/METADATA
dopplrSDKtest-1.11.dist-info/WHEEL
dopplrSDKtest-1.11.dist-info/top_level.txt
dopplrSDKtest-1.11.dist-info/RECORD
