Metadata-Version: 2.1
Name: dopplrSDKtest
Version: 1.11
Summary: UNKNOWN
Home-page: UNKNOWN
Author: Anand
Author-email: anandt@systechusa.com
License: UNKNOWN
Platform: UNKNOWN
Classifier: Programming Language :: Python :: 3
Classifier: License :: OSI Approved :: MIT License
Classifier: Operating System :: OS Independent
Requires-Dist: psycopg2-binary (==2.9.9)
Requires-Dist: pandas (==2.2.0)
Requires-Dist: boto3 (==1.26.153)
Requires-Dist: pycryptodome (==3.18.0)
Requires-Dist: cryptography (==41.0.1)
Requires-Dist: azure-storage-blob (==12.15.0)
Requires-Dist: botocore (==1.29.153)
